notify_mi/__init__.py
notify_mi/helper.py
notify_mi/notify.py
notify_mi/providers.py
notify_mi-1.0.3.dist-info/LICENSE
notify_mi-1.0.3.dist-info/METADATA
notify_mi-1.0.3.dist-info/WHEEL
notify_mi-1.0.3.dist-info/top_level.txt
notify_mi-1.0.3.dist-info/RECORD
