Metadata-Version: 2.1
Name: notify-mi
Version: 1.0.3
Summary: Notify Mi simplifies sending yourself text and email notifcations from your personal projects by utilizing your gmail account.
Home-page: https://github.com/Amark18/notify_mi
Author: Amar Khanshali
Author-email: akhanshali@gmail.com
Project-URL: Bug Tracker, https://github.com/Amark18/notify_mi/issues
Keywords: sms,mms,email,text-notifications,email-notifications,gmail-smtp,file-attachment
Classifier: Programming Language :: Python :: 3
Classifier: License :: OSI Approved :: MIT License
Classifier: Operating System :: OS Independent
Requires-Python: >=3
License-File: LICENSE
